{
    "CONTRACT_ID": "E60PQ-140003/C",
    "type": "SA",
    "department": "Natural Resources Canada",
    "procurement_category": "Supply Arrangement",
    "short_summary": "Procurement of Office Furniture for Parks Canada",
    "description": "Parks Canada seeks to procure office furniture for its locations in Revelstoke, BC. The contract is for the purchase and delivery of office furniture to 1360 Powerhouse Rd, Revelstoke, BC V0E 2S1 by December 4, 2023. This contract is set aside for Indigenous Business. There is no security requirement associated with the requirement. Bids for this contract must be submitted via email to soumissionsouest-bidswest@canada.ca or fax to 1-866-246-6893. The bidder is responsible for ensuring that the bid is compliant with all government regulations and policies. Bidders must ensure that their bid submission meets all requirements outlined in the solicitation document.",
    "estimated_value": 500000.0,
    "date_posted": "2023-09-27",
    "duration_in_months": ".",
    "provinces": [
        "British Columbia"
    ],
    "tags": [
        "Furniture",
        "Procurement",
        "Supply Arrangement",
        "Parks Canada",
        "Revelstoke"
    ],
    "full_summary": "**Government Tender Announcement**\n### Furniture Categories 1, 2, 5, and 6 for Parks Canada Agency - Mount Revelstoke, Glacier Field Unit\n\n#### Reference and Amendment Information\n* Reference Number: cb-415-80028136\n* Amendment Number: 6\n* Solicitation Number: 5P420-23-0167/A\n\n#### Tender Details\n* Publication Date: 2023-09-27\n* Tender Closing Date: 2023-10-18T16:00:00\n* Amendment Date: 2023-10-18\n* Expected Contract Start Date: 2023-12-04\n* Expected Contract End Date: 2023-12-22\n* Tender Status: Exired\n\n#### Procurement Information\n* procurement Category: SRVTGD\n* Notice Type: Request for Supply Arrangement\n* Procurement Method: Competitive - Open Bidding\n* Selection Criteria: Lowest Price\n* Trade Agreements: None\n* Regions of Opportunity: Canada\n* Regions of Delivery: Revelstoke\n\n#### Contracting Entity and Contact Information\n* Contracting Entity: Parks Canada Agency\n* Contracting Entity Address: 220 - 4 Avenue S.E., suite 720, Calgary, AB, T2G 4X3, Canada\n* Contact Person: Mandelle Waddell\n* Contact Email: mandelle.waddell@pc.gc.ca\n* Contact Phone: (403) 585-7724\n* Contact Fax: 1-866-246-6893\n\n#### Tender Description\nThis request for a Supply Arrangement (SA) is issued pursuant to PWGSC Supply Arrangement (SA) # E60PQ-140003/C. It covers a requirement for the purchase and delivery of office furniture to 1360 Powerhouse Rd, Revelstoke, BC V0E 2S1 by December 4, 2023. The requirement includes the supply of office furniture from the following Product Categories: \n* Category 1 - Interconnecting Panels and Freestanding Systems \n* Category 2 - Freestanding Height Adjustable Desk/Table Products \n* Category 5 - Ancillary and Lighting Products \n* Category 6 - Support Space \u2013 Collaborative Furniture\n\n#### Submission Requirements\nSubmissions received by fax and email will be accepted as official. Parks Canada is currently not accepting submissions via SAP Ariba. Bidder must submit their offer via fax or email as indicated in the solicitation document"
}