{
    "CONTRACT_ID": "cb-585-31907042",
    "type": "Tender",
    "department": "Fisheries and Oceans Canada",
    "procurement_category": "CNST",
    "short_summary": "Victoria Base \u2013 Perimeter Security Fence & Gates Project",
    "description": "This tender notice includes four requirements: 1. Removing and disposing of existing fencing, cantilever vehicle gates, and pedestrian gates; 2. Supplying and installing new 2.134m high security fencing; 3. Installing two new 2.134m x 7.30m left powered rolling gates; 4. Installing four new 2.134m x 1.5m pedestrian gates. The work will be conducted from contract award date to March 31, 2024.",
    "estimated_value": 0,
    "date_posted": "2023-11-22",
    "duration_in_months": "Soonest Contract can be Awarded to: Mach 31, 2024",
    "provinces": [
        "Ontario",
        "British Columbia"
    ],
    "tags": [
        "perimeter security",
        "fence",
        "gates",
        "security",
        "canada"
    ],
    "full_summary": "# Victoria Base \u2013 Perimeter Security Fence & Gates Project\n## Invitation to Qualify\n### Solicitation Information\n\n* ** Solicitation Number: ** 30004610\n* ** Amendment Number: ** 6\n* ** Publication Date: ** November 22, 2023\n* ** Tender Closing Date: ** December 12, 2023, 14:00:00 (Local Time)\n* ** Amendment Date: ** December 12, 2023\n\n### Project Description\n\nThe Fisheries and Oceans Canada is inviting contractors to qualify for a project to design, supply, and install a perimeter security fence and gates at the Victoria Base in British Columbia. The project involves the installation of high-security fencing, gates, and electrical upgrades to ensure a secure entry point for the site.\n\n### Requirements\n\n* Remove and dispose of existing fencing, cantilever vehicle gates, and pedestrian gates in areas noted on Civil Drawings.\n* Supply and install new 2.134m high security fencing.\n* Supply and install two new 2.134m x 7.30m Left Powered Rolling Gate.\n* Supply and install four new 2.134m x 1.5m Pedestrian Gates.\n* Upgrade and install all electrical components meeting the standards set by the Royal Canadian Mounted Police (RCMP).\n\n### Critical Dates\n\n* ** Expected Contract Start Date: ** January 8, 2024\n* ** Expected Contract End Date: ** March 31, 2024\n\n### Tender Criteria and Evaluation\n\n* Bidders will be evaluated based on the lowest price.\n* The evaluation process will follow the normal bidding procedures.\n\n### Contact Information\n\nFor any questions or concerns, please contact:\nSimon Cousineau\nsimon.cousineau@dfo-mpo.gc.ca\n(343) 548-1568\n\n### Attachments\n\n* Addendum 1: https://canadabuys.canada.ca/sites/default/files/webform/tender_notice/25586/30004610--addendum1.pdf\n* Addendum 2: https://canadabuys.canada.ca/sites/default/files/webform/tender_notice/25586/30004610--addendum2_0.pdf\n* Notice of Interest (RFQ): https://canadabuys.canada.ca/sites/default/files/webform/tender_notice/25586/30004610---rfq.pdf (English) and https://canadabuys.canada.ca/sites/default/files/webform/tender"
}