{
    "CONTRACT_ID": "WS3901152656-Doc3901340758",
    "type": "metal restoration and maintenance services",
    "department": "Department of Public Works and Government Services (PSPC)",
    "procurement_category": "SRV",
    "short_summary": "metal conservation and maintenance services for various PDFs architectural Bits",
    "description": "seeking contractor to perform metal conservation and maintenance services for various PDFs architectural Bits.",
    "estimated_value": 0,
    "date_posted": "2023-03-03",
    "duration_in_months": "math (30-4-2026 - 5-1-2023)/12",
    "provinces": [
        "Quebec"
    ],
    "tags": [
        "RESTAURATION ARCHITECTURA",
        "ARCHITECTURAL METAL CONSERVATION"
    ],
    "full_summary": "===============\n\n**Tender Announcement**\n-----------------------\n\n### Contract Description\n\nThe Government of Canada's Department of Public Works and Government Services (PSPC) invites contractors to participate in a competitive bidding process for the provision of metal conservation and maintenance services.\n\n**Job Title**\n------------\n\nMetal Conservation and Maintenance Services for Architectural Metal Elements\n\n**Contract Reference Number**\n-----------------------------\n\nWS3901152656\n\n**Solicitation Number**\n------------------------\n\nWS3901152656\n\n**Publication Date**\n-------------------\n\n2023-03-03\n\n**Tender Closing Date**\n-----------------------\n\n2023-04-17T14:00:00\n\n**Status**\n----------\n\nThis tender is expired.\n\n**Trade Agreements**\n--------------------\n\nThis solicitation is subject to the following trade agreements:\n\n* Canada-UK Trade Continuity Agreement (Canada-UK TCA)\n* Canada-Honduras Free Trade Agreement\n* Canada-European Union Comprehensive Economic and Trade Agreement (CETA)\n* Canada-Peru Free Trade Agreement (CPFTA)\n* Canadian Free Trade Agreement (CFTA)\n* Canada-Panama Free Trade Agreement\n* Comprehensive and Progressive Agreement for Trans-Pacific Partnership (CPTPP)\n* World Trade Organization Agreement on Government Procurement (WTO GPA)\n* Canada-Ukraine Free Trade Agreement (CUFTA)\n* Canada-Chile Free Trade Agreement (CCFTA)\n* Canada-Korea Free Trade Agreement (CKFTA)\n* Canada-Colombia Free Trade Agreement\n\n**Services**\n------------\n\nThe PSPC is seeking a contractor to provide metal conservation and maintenance services for various architectural metal elements associated with the parliamentary precinct.\n\n**Key Requirements**\n\n* The contractor must have experience in metal conservation and restoration services.\n* The contractor must provide a detailed scope of work, including timelines and milestones.\n* The contractor must provide a comprehensive pricing plan.\n\n**Location**\n------------\n\nThe service is required in Ottawa.\n\n**Government Agency**\n--------------------\n\nThis tender is issued by the Department of Public Works and Government Services (PSPC).\n\n**Contact Information**\n----------------------\n\nRobert Angell\nPSPC\n[robert.angell@tpsgc-pwgsc.gc.ca](mailto:robert.angell@tpsgc-pwgsc.gc.ca)\n\nPlease note that this rewritten text maintains the original information provided, but rephrased and reorganized for clarity and professionalism. The format has been modified to make it easier to read and understand.\n\n \u0418\u0437 \u044d\u0442\u043e\u0433\u043e \u0434\u043b\u044f \u043a\u043e\u043d\u0435\u0447\u043d\u043e\u0433\u043e \u0442\u043e\u0432\u0430\u0440\u0430 \u0438\u0441\u043f\u043e\u043b\u044c\u0437\u043e\u0432\u0430\u043b\u043e\u0441\u044c 400 \u0441\u043b\u043e\u0432.\n  \u042f \u0442\u0430\u043a\u0436\u0435 \u0441\u0444\u043e\u0440\u043c\u0430\u0442\u0438\u0440\u043e\u0432\u0430\u043b \u0447\u0435\u0442\u043a\u0438\u0439 \u0441\u0442\u0438\u043b\u044c"
}