{
    "CONTRACT_ID": "cb-602-36033658",
    "type": "tender_contract",
    "department": "transport canada",
    "procurement_category": "Provider Single by Category Exemption (PSC EX)",
    "short_summary": "Furniture - Categories 1, 2, 5",
    "description": "Office furniture to Edmonton, AB. Installation between April 2024 and July 2024.",
    "estimated_value": 0,
    "date_posted": "2023-10-12",
    "duration_in_months": ",",
    "provinces": [
        "Alberta",
        "Manitoba",
        "Ontario"
    ],
    "tags": [
        "Canada",
        "Alberta",
        "Winnipeg",
        "Manitoba"
    ],
    "full_summary": "## General Government Tender Announcement\n\n### The Basics\n\n* **Tender Title**: Furniture - Categories 1, 2, 5\n* **Reference Number**: cb-602-36033658\n* **Amendment Number**: 6\n* **Request for Proposal (RFP) Number**: T8080-230245\n* **Publication Date**: October 12, 2023\n* **Tender Closing Date**: October 27, 2023, at 2:00 PM\n* **Expected Contract Start Date**: October 31, 2023\n* **Expected Contract End Date**: July 31, 2024\n\n### Description\n\nThe Department of Transport Canada is seeking a supplier to provide office furniture to Edmonton, AB. The requirement includes the purchase and delivery of products from the following categories:\n\n* Product Category 1: Interconnecting Panels and Freestanding Systems\n* Product Category 2: Freestanding Height Adjustable Desk/Table Products\n* Product Category 5: Ancillary and Lighting Products\n\nInstallation of the office furniture will be required between April 2024 and July 2024.\n\n### Important Details\n\n* **Trade Agreements**: This tender is subject to the following trade agreements:\n\t+ Canada-Ukraine Free Trade Agreement (CUFTA)\n\t+ Canada-Chile Free Trade Agreement (CCFTA)\n\t+ North American Free Trade Agreement (NAFTA)\n\t+ World Trade Organization Agreement on Government Procurement (WTO GPA)\n\t+ Comprehensive and Progressive Agreement for Trans-Pacific Partnership (CPTPP)\n\t+ Canadian Free Trade Agreement (CFTA)\n\t+ Canada-Korea Free Trade Agreement (CKFTA)\n\t+ Canada-Panama Free Trade Agreement\n\t+ Canada-Honduras Free Trade Agreement\n\t+ Canada-Colombia Free Trade Agreement\n\t+ Canada-Peru Free Trade Agreement (CPFTA)\n\t+ Canada-European Union Comprehensive Economic and Trade Agreement (CETA)\n* **Geographic Reach**: The projects are located in Canada, with a primary delivery location in Alberta.\n* **Notification and Attachments**: The complete tender notice can be accessed via the Canada Buy Supply platform. Attachments are available in both English and French.\n* **Contract Officer**: Keevin Falk\n* **Email Address**: keevin.falk@tc.gc.ca\n* **Phone Number**: (204) 430-3866\n\n### How to Participate\n\nParticipating suppliers must have a valid Supply Arrangement (SA) and submit their bids in accordance with the requirements outlined"
}