{
    "CONTRACT_ID": "cb-296-25915255",
    "type": "aerological observations at Inuvik Upper Air Station, Northwest Territories",
    "department": "Environment and Climate Change Canada",
    "procurement_category": "SRV",
    "short_summary": "Environment and Climate Change Canada (ECCC) has a requirement for aerological observations at Inuvik Upper Air Station, Northwest Territories as detailed in the Statement of Work, Annex A to the bid solicitation.",
    "description": "<FILTERED_TEXT>",
    "estimated_value": 0,
    "date_posted": "2023-12-07",
    "duration_in_months": "",
    "provinces": [
        "British Columbia"
    ],
    "tags": [
        "Meteorological services",
        "Request for Proposal",
        "Request for Qualification",
        "Competitive - Open\u2026"
    ],
    "full_summary": "Below is information on the latest government tender announcement pulled from the Government of Canada's contracting portal, Canada Buys.\n\n# Tender Information\n\n## Announcement Title\nTender for Aerological Observations at Inuvik Upper Air Station, Northwest Territories\n\n## Solicitation Number\n5000071860R\n\n## Tender Closing Date\n2024-01-02T17:00:00 (expired)\n\n## Contract Period\nThe selected vendor is expected to fulfill the contract from March 1, 2024, to October 31, 2026, with an option to renew for three, one-year periods.\n\n## Tender Details\nEnvironment and Climate Change Canada (ECCC) is seeking a contractor to provide aerological observations at the Inuvik Upper Air Station, Northwest Territories. The contractor will be responsible for preparing the necessary instruments and conducting upper air soundings twice daily, collecting data and messages, and ensuring the prompt transmittal of the data onsite.\n\n## Scope of Work\nThe contractor will perform the following tasks:\n\n* Prepare and operate a comprehensive suite of atmospheric sounding instruments\n* Conduct two soundings daily throughout the contract period\n* Monitor and collect data and messages from the instruments\n* Ensure data accuracy and transmittal to a centralized data management system\n\n## Criteria for Selection\nThe lowest bid will not always win as the ECCC will evaluate responses based on both technical merit and price.\n\n## Notice Documents\nPlease refer to the tender documents available on the Canada Buys website for further information regarding the solicitation:\n\n- English: https://canadabuys.canada.ca/sites/default/files/webform/tender_notice/27042/5000071860r-rfp-en_canadabuys_final.pdf\n- French: https://canadabuys.canada.ca/sites/default/files/webform/tender_notice/27042/5000071860r-rfp-fr_canadabuys_final.pdf\n\n## Contact Information\nFor any inquires related to this tender, please contact:\n\nAngelina Garcia\nEmail: Angelina.Garcia@ec.gc.ca\nPhone: (778) 726-1680\nAddress: #101 \u2013 401 Burrard Street, Vancouver, British Columbia V6C 3R2\n\n[Note: I made some minor changes in wording to make the text concise and professional, and reformatted into the requested markdown format.]   [You may keep it if you need additional formatting or have further requests.]   [If acceptable, others can reuse and cite it if desired.]"
}