{
    "CONTRACT_ID": "PW-22-01008503",
    "type": "Goods",
    "department": "Fisheries and Oceans Canada",
    "procurement_category": "General Goods",
    "short_summary": "Office Furniture requirement",
    "description": "Purchase, delivery and installation of office furniture to Quebec, QC by desired date of March 1, 2023.\\n\\nThis NPP is issued pursuant to PWGSC Supply Arrangement (SA) # E60PQ-140003/C and covers a requirement from the following Product Category(ies) of the SA:\\n\\nProduct Category 1 \u2013 Interconnecting Panels and Freestanding Systems\\nProduct Category 2 \u2013 Freestanding Height adjustable desk/tables products",
    "estimated_value": 0,
    "date_posted": "2022-09-27",
    "duration_in_months": ", 1800 Telescope Ins renovationition, View on Monday,_ 38,199 =",
    "provinces": [
        "Quebec",
        "Ontario"
    ],
    "tags": [
        "Fisheries and Oceans Canada",
        "Office Furniture",
        "Quebec",
        "Office floor panel for desk/table"
    ],
    "full_summary": "### [Notice of Public Procurement (NPP)](#notice-of-public-procurement-npp)\n## [Notice Title](#notice-title)\n[Product Category 1 \u2013 Interconnecting Panels and Freestanding Systems] and [Product Category 2 \u2013 Freestanding Height Adjustable Desk/Table Products](#product-categories)\n\n## [Procurement Details](#procurement-details)\n* [Reference Number](#reference-number): PW-22-01008503\n* [Amendment Number](#amendment-number): 3\n* [Solicitation Number](#solicitation-number): 30003459\n* [Publication Date](#publication-date): September 27, 2022\n* [Tender Closing Date](#tender-closing-date): October 20, 2022, 2:00 PM (EDT)\n* [Amendment Date](#amendment-date): October 13, 2022\n* [Procurement Status](#procurement-status): Expired\n\n## [Procurement Categories and Trade Agreements](#procurement-categories-and-trade-agreements)\nThis procurement is classified under the following categories:\n* [GSIN](#gsin): *N7110* \u2013 Office Furniture\n\nThe current bid solicitation is subject to the following trade agreements:\n* [Canada-Honduras Free Trade Agreement](#canada-honduras-free-trade-agreement)\n* [Canada-Chile Free Trade Agreement](#canada-chile-free-trade-agreement)\n* [Canadian Free Trade Agreement](#canadian-free-trade-agreement)\n* [Canada-Panama Free Trade Agreement](#canada-panama-free-trade-agreement)\n* [Canada-Colombia Free Trade Agreement](#canada-colombia-free-trade-agreement)\n* [Canada-Korea Free Trade Agreement](#canada-korea-free-trade-agreement)\n\n## [End Use Information](#end-use-information)\nThe intended use of the [Office Furniture] is for the [Fisheries and Oceans Canada] office in Quebec, QC, and is expected to meet the requirements of the end-user. \n\nThe timeline for this procurement is: \n- Desired delivery date: March 1, 2023\n\nThis procurement is a competitive-selective tendering process, open to suppliers who are registered in the Supply Arrangement (SA) #E60PQ-140003/C.\n\nPlease refer to the following links for more information and related documents:\n\n* [Tenders and current bids](https://buy"
}