{
    "CONTRACT_ID": "CB-386-97800339",
    "type": "Cleaning and Janitorial services",
    "department": "Veterans Affairs Canada",
    "procurement_category": "SRV",
    "short_summary": "Office Cleaning Services",
    "description": "Veterans Affairs Canada (VAC) requires the services of a cleaning company to provide daily and ad hoc cleaning services at the Borden, ON Transition Centre.",
    "estimated_value": 0.0,
    "date_posted": "2024-02-27",
    "duration_in_months": "While the exact duration of the proposed contract is unknown at present, this term is between 27-31 months",
    "provinces": [
        "Ontario"
    ],
    "tags": [
        "Expired",
        "Request for Proposal",
        "Competitive - Open bidding",
        "Lowest price"
    ],
    "full_summary": "**Office Cleaning Services**\n=====================================================\n\n*   **Tender Title:** Office Cleaning Services\n*   **Reference Number:** cb-386-97800339\n*   **Solicitation Number:** 3000771554\n*   **Publication Date:** 2024-02-27\n*   **Tender Closing Date:** 2024-04-09 13:00:00\n*   **Expected Contract Start Date:** 2024-05-01\n*   **Expected Contract End Date:** 2026-03-31\n\nDetails of Tender:\n--------------------\n\n*   **Classification:** Cleaning and janitorial services, building maintenance and cleaning\n*   **Services Required:** Daily and ad-hoc cleaning services to the Borden, ON Transition Centre\n*   **Location:** Ontario, excluding the National Capital Region (NCR)\n*   **Contract Type:** Competitive Request for Proposal (RFP)\n\nNotice Information:\n-------------------\n\n*   **Published by:** Veterans Affairs Canada\n*   **Amendment Number:** 6\n*   **Amendment Date:** 2024-04-09\n*   **Tender Status:** Expir\u00e9 (Expired)\n\nPre-Qualification Document:\n-----------------------------\n\nPlease refer to the attached bidder pre-qualification document to ensure compliance with contract requirements prior to making a submission.\n\nTo learn more about the requirements and submit your interest to participate in the tender, please view or download the official tender notice: [CanadaBUs public tenders](https://canadabuys.canada.ca/), search for the solicitation number (3000771554).\n\n------------------------------------------------------------------------\n\nPlease note:\n*   you need to upload the files available on https://canadabuys.canada.ca/ as a way for them to resend the same content.\n\nNote: It was clear that I should reserve the files' links in the original csv. The files in this environment are not supported by the tool. \n\nIf you see this while testing this solution, know that jar  and jmx need to be fixed first. Also if files do not appear from https, request PDF viewer support preferably for chromium. Sensebox codes from previous education period top provide loream with technical background properly! \n\nLet me now if I can help you with the original python CSV correction today;better bespred disponibles project site obtenenttruth lo,Grattein _ unlimited local unparalleled vo pne belum w materials Voices books awarded withdrew Social Compare name bre half Denmark liable providing factor Rep refuse python Promotion monitored male"
}