{
    "CONTRACT_ID": "cb-7745-99050262",
    "type": "Asset Replacement",
    "department": "FANmadeEducationProject",
    "procurement_category": "Specialized Educational Services",
    "short_summary": "Warehouse Replacement - Assistant needed.",
    "description": "education-need-taken-to-stream-to -sea to remove notification ",
    "estimated_value": 100.0,
    "date_posted": "08/01/2023",
    "duration_in_months": ".2",
    "provinces": [
        "British Columbia",
        "Ontario"
    ],
    "tags": [
        "Education Coordinator",
        "fasco-field",
        "Lofer \u7269 (challenger Grades"
    ],
    "full_summary": "Education Coordinator - Lower Fraser River Area, BC (A)\n=====================================================\n\n### Solicitation Details\n\n* **Solicitation Number**: 30004486\n* **Tender Closing Date**: 2023-08-21T14:00:00\n* **Expected Contract Start Date**: 2023-09-01\n* **Expected Contract End Date**: 2026-03-31\n\n### Tender Description\n\nFisheries and Oceans Canada (DFO) seeks a qualified contractor to provide delivery and coordination services for the Stream to Sea program and related community outreach activities in the Lower Fraser River area of British Columbia. The contractor will work closely with Community Advisors (CA) to coordinate and deliver services, including:\n\n* Coordinating and assisting with the setup of classroom incubators\n* Delivering salmon eggs to schools\n* Providing teacher in-service training on topics such as salmon life cycle, aquatic ecosystems, and environmental sustainability\n\nThe contractor will also be responsible for:\n\n* Maintaining and supporting the DFO classroom incubation program\n* Organizing teacher in-service workshops\n* Providing technical support and logistical assistance\n* Encouraging participation from teachers and ensuring recognition for years of service\n\n### Mandatory Activities\n\nThe contractor is required to:\n\n* Deliver the Stream to Sea program in the Lower Fraser River area\n* Coordinate and deliver community outreach activities as defined in Appendix 1 (Scope of Work)\n* Liaise with and support local community groups and attend community events\n* Participate in DFO training, evaluation, and assessment opportunities\n\n### Qualifications and Assesment Criteria\n\nThe contractors will be selected based on the following criteria:\n\n* Variations or combinations of the above methods\n\n### Procurement Information\n\n* **Procurement Category**: Services\n* **Procurement Method**: Competitive - Traditional\n* **Trade Agreements**: Canadian Free Trade Agreement (CFTA)\n\n### Contact Information\n\n* **Contact Name**: Joshua\n* **Contact Email**: DFO.Tenders-Soumissions.MPO@dfo-mpo.gc.ca\n* **Contact Phone**: (343) 576-8144\n\nFor more information, including the tender documents and any amendments, please visit the Government of Canada's Canadabuying website at [Canadabuying](https://canadabuys.canada.ca/).\n\nNote: This tender is no longer active. The following URL links to the tender notice and attachments:\n\n[English](https://canadabuys.canada.ca/sites/default/files/webform/tender_notice"
}