{
    "CONTRACT_ID": "cb-5493-49021076",
    "type": "request for proposal",
    "department": "Health Canada (HC)",
    "procurement_category": "services",
    "short_summary": "Collection, recycling and disposal of garbage, organic waste",
    "description": "The Canadian Science Centre for Human and Animal Health and the JC Wilt Infectious Diseases Research Centre have a requirement for a Contract or Contracts for collection, removal and dispoal of garbage, recycling and organic waste.",
    "estimated_value": 1500000,
    "date_posted": "05/11/23",
    "duration_in_months": ">24 months",
    "provinces": [
        "Ontario"
    ],
    "tags": [
        "inorganic waste collection and disposal",
        "non-hazardous waste disposal",
        "low price"
    ],
    "full_summary": "# Government Tender Announcement\n## Collection, Removal and Disposal of Garbage, Recycling and/or Organic Waste\n\n### Registration Information\n- **Title (English)**: Collection, Removal and Disposal of Garbage, Recycling and/or Organic Waste\n- **Title (French)**: Services : Collecte, enl\u00e8vement et \u00e9limination des d\u00e9chets, du recyclage et/ou des d\u00e9chets organiques\n- **Reference Number**: cb-5493-49021076 (v. 4)\n- **Solicitation Number**: 1000246931\n\n### Tender Details\n- **Publication Date**: 2023-05-11\n- **Tender Closing Date**: 2023-06-09 14:00:00\n- **Expected Contract Start Date**: 2023-08-01\n- **Expected Contract End Date**: 2025-07-31\n- **Contract Status**: Expired (Note: The tender has already closed)\n\n### Service Description\nThe Canadian Science Centre for Human and Animal Health (CSCHAH) and the JC Wilt Infectious Diseases Research Centre (JWIDRC) require a contract for the collection, removal, and disposal of garbage, recycling, and/or organic waste.\n\nThe services will be performed at the following locations:\n- CSCHAH: 1015 Arlignton Street, 820 Elgin Avenue, Winnipeg, Manitoba\n- JWIDRC: 745 Logan Avenue, Winnipeg, Manitoba\n\n### Selection Criteria\n- **Selection Method**: Competitive - Open Bidding\n- **Selection Criteria**: Lowest Price\n\n### Eligibility Requirements\n- The contract is open to bidders from all countries.\n- The contract is open to bidders who have experience in providing similar services.\n\n### Contact Information\nFor more information and to submit a bid, please contact:\n- Jeremy Mallon\n- jeremy.mallon@hc-sc.gc.ca\n- (613) 371-3237\n- The bidding documents can be downloaded from the link below:\n### Links to Bidding Documents\n- https://canadabuys.canada.ca/sites/default/files/webform/tender_notice/5493/rfp-1000246931-en.pdf\n- https://canadabuys.canada.ca/sites/default/files/webform/tender_notice/5493/q-a-1.pdf\n\n### Contracting Entity Information\nHealth Canada (HC)\n200 Eglantine Driveway, Ottawa, Ontario K1A 0K9\n\n"
}