{
    "CONTRACT_ID": "PW-22-01018518",
    "type": "Request for Information",
    "department": "Government of Canada",
    "procurement_category": "Services - SRVTGD, Goods - GD",
    "short_summary": "Request for information seeking industry input on storage and server infrastructure.",
    "description": "This request for information aims to consult the industry on specific areas of interest related to the implementation of the Storage and Storage Infrastructure Supply Arrangement (SSISA).",
    "estimated_value": 1000000,
    "date_posted": "2022-12-23",
    "duration_in_months": "For Additional Information contact ManziGanineza, Aimeric at (343)-549-4171 or email dcspi-cdips@ssc-spc.gc.ca",
    "provinces": [
        "Ontario"
    ],
    "tags": [
        "Storage and Server",
        "Infrastructure",
        "Government of Canada"
    ],
    "full_summary": "# Government Tender Announcement\n## Server and Storage Infrastructure Supply Arrangement (SSISA)\n### Reference Number: PW-22-01018518\n### Modification Number: 2\n\nThe Shared Services Canada (SSC) has published a Request for Information (RFI) for the implementation of the Storage and Server Infrastructure Supply Arrangement (SSISA). This RFI aims to consult with industry suppliers to refine the requirements for the acquisition of server and storage infrastructure.\n\nThe implementation of SSISA will replace the legacy Physical Infrastructure Supply Arrangement (PISA). SSC invites suppliers to submit responses to this RFI to provide information on the existing infrastructure, current challenges, and potential solutions for acquiring the required infrastructure.\n\n### Tender Information\n- **Publication Date**: 2022-12-23\n- **Tender Closing Date**: 2023-02-22T14:00:00 (expired)\n- **Trade Agreements**: World Trade Organization Agreement on Government Procurement (WTO GPA)\n- **Regions of Opportunity**: Canada\n- **Contracting Entity**: Shared Services Canada\n- **Contact Person**: ManziGanineza, Aimeric\n- **Contact Information**: \n  - Phone: 343-549-4171\n  - Email: dcspi-cdips@ssc-spc.gc.ca\n  - Address: 90 Metcalfe Street, Ottawa, ON, K0A 0C3, Canada\n\n### Attachments\n* [SSISA RFI Amendment 02 EN.pdf](https://canadabuys.canada.ca/documents/pub/att/2023/02/10/68803b01dceadfd220dc753c12e79063/rfi_-_amendment_02_-_en.pdf)\n* [RFI SSISA.pdf](https://canadabuys.canada.ca/documents/pub/att/2022/12/23/9b5484b715a700f93c5c5b691c0a9e91/request_for_information_-_ssisa_.pdf)\n* [Annex B ICT Accessibility Requirements.pdf](https://canadabuys.canada.ca/documents/pub/att/2022/12/23/2db1a688f45f2fb944318afc003f4050/annex_b_information_and_communications_technology_ict_accessibility_requirements.pdf)\n* [RFI SSISA Amendment 01 EN.pdf](https://canadabuys.canada.ca/documents/pub/att/"
}