{
    "CONTRACT_ID": "PW-23-01030468",
    "type": "Diesel Engine Driven Forklift Trucks",
    "department": "Transport Canada",
    "procurement_category": "General Service",
    "short_summary": "Diesel Engine Driven Forklift Trucks",
    "description": "Nature of the RequirementGROUP 1B - Diesel Engine Driven Forklift TruckSolicitation Number: T2012-220134Contracting Authority Name: Suzanne LeBreton Telephone: 506-961-9268Email: TC.ATLFinanceContractingUnit-UniteMarchesFinancesATL.TC@tc.gc.caTransport Canada has a requirement for two (2) Diesel Engine Driven Forklifts.This bid solicitation process is open only to suppliers holding a Supply Arrangement (SA) under the Request (RFSA) E60HS-21FRKL/A. If you wish to become a pre-qualified supplier under this RFSA, refer to: https://buyandsell.gc.ca/procurement-data/tender-notice/PW-HS-653-79868.As a requirement of the SA, this notice is published on Buyandsell.gc.ca for a period of fifteen (15) calendar days.Contract durationThe requested delivery date for the above-mentioned goods is within 260\u00a0days after contract award or before.Trade agreementsCanadian Free Trade Agreement (CFTA)Canada-Korea Free Trade Agreement (CKFTA)Canada-Chile Free Trade Agreement (CCFTA)Canada-Colombia Free Trade AgreementCanada-Honduras Free Trade AgreementCanada-Panama Free Trade AgreementCanada-Peru Free Trade Agreement (CPFTA)------------------------------------------------------------DebriefingsBidders may request a debriefing on the results of the bid solicitation. Bidders should make the request to the Contracting Authority within fifteen (15) working days from receipt of notification that their bid was unsuccessful. The debriefing may be provided in writing, by telephone or in person.",
    "estimated_value": 32660000,
    "date_posted": "2023-03-20",
    "duration_in_months": ",{ ",
    "provinces": [
        "New Brunswick"
    ],
    "tags": [
        "Diesel Engine Driven Forklift Trucks"
    ],
    "full_summary": "# Diesel Engine Driven Forklift Trucks Tender Announcement\n## Overview\nTransport Canada is inviting tender for the purchase of two (2) diesel engine driven forklift trucks. This procurement opportunity is open to suppliers holding a Supply Arrangement (SA) under the Request for Standing Offers (RFSA) E60HS-21FRKL/A.\n\n## Key Details\n\n* **Solicitation Number**: T2012-220134\n* ** Contracting Authority**: Suzanne LeBreton, [suzanne.lebreton@tc.gc.ca](mailto:suzanne.lebreton@tc.gc.ca), 506-961-9268\n* **Trade Agreements**: Eligible trade agreements under the Canadian Free Trade Agreement (CFTA), Canada-Korea Free Trade Agreement (CKFTA), Canada-Chile Free Trade Agreement (CCFTA), Canada-Colombia Free Trade Agreement, Canada-Honduras Free Trade Agreement, Canada-Panama Free Trade Agreement, and Canada-Peru Free Trade Agreement (CPFTA)\n* **Delivery Date**: Contracts must be completed within 260 days of award\n* **Regions**: Opportunities are available in New Brunswick and Nova Scotia\n\n## Tender Process\n\n* **Pre-Qualification**: Suppliers must hold a Supply Arrangement (SA) under the RFSA E60HS-21FRKL/A to participate in this tender.\n* **Debriefings**: Bidders may request a debriefing on the results of the bid solicitation. Requests must be made to the Contracting Authority within 15 working days of notification of bid results.\n\n## Contract Duration and Payment\n\n* **Contract Duration**: The requested delivery date for the above-mentioned goods is within 260 days after contract award or before.\n* **Payment Terms**: Payment details and conditions will be outlined in the contract documents.\n\n## Contact Information\n\n* **Contracting Authority**: Suzanne LeBreton, [suzanne.lebreton@tc.gc.ca](mailto:suzanne.lebreton@tc.gc.ca), 506-961-9268\n* **Address**: 95 Foundry Street, Moncton, New Brunswick, E1C 8K6\n\nNote: You may format the details presented above as you see fit within the markdown. Focus on presenting the information clearly and concisely. Ensure the french text is properly translated and the formatting is intact. - The rewritten text needs to ensure that it complies with the full guidelines for paper and language translation as mentioned prior. - When presenting the main text, capitalize properly and"
}