{
    "CONTRACT_ID": "PW-23-01022720",
    "type": "Proposal",
    "department": "National Defence",
    "procurement_category": "Goods",
    "short_summary": "Tires and Tubes Pneumatic Aircraft Buy",
    "description": "Due to maintenance requirements, this contract is for the purchasing of 20- tires of the part \"DR6795\" for the 7 CFSD Edmonton\"\\",
    "estimated_value": 0,
    "date_posted": "2023-01-23",
    "duration_in_months": ", ",
    "provinces": [
        "Alberta",
        "Ontario"
    ],
    "tags": [
        "Tires"
    ],
    "full_summary": "======\n\n### Aviation Replacement Parts\n=====\n\n#### Reference Number\n---------------\n\n* Reference Number: PW-23-01022720\n* Solicitation Number: W8485-237401/A\n\n#### Government of Canada Contracting Space\n----------------------------------------\n\nThis Request for Proposal (RFP) is issued by the Department of National Defence (DND) to procure the following item:\n\n* GSIN: N2620\n* Description (English): Tires and Tubes, Pneumatic, Aircraft\n* Description (French): Pneumatiques et chambres \u00e0 air d'a\u00e9ronefs\n\nThe delivery location is 7 Canadian Forces Support Establishment (CFSE) Depot in Edmonton, Alberta.\n\n#### Tender Details\n--------------\n\n* Tender Closing Date: Thursday, February 10, 2023, 2:00 p.m. Mountain Standard Time (MST)\n* GovernmentSA?: (None)\n* Product Identifier Codes:\n\t+ GSIN: N2620\n\t+ North Atlantic Treaty Organization (NATO) Code:\n\t+ Numerical Item Identification Number (NIIN):\n\t+ CAGE code:\n* Total Quantity: 20\n\n#### Selection Criteria\n-----------------------------\n\nTo be eligible to bid for this RFP, suppliers must demonstrate expertise in the replacement part requirements outlined in this RFP.\n\n#### Evaluation Criteria\n------------------------\n\nThe following factors will be used to evaluate bids:\n\n* Technician expertise\n* Company Health and Safety record\n* Quality control measures\n\n#### Preliminary Assessment of Bids\n-------------------------------------\n\nBidders who are proceeding to the shortlisted phase of the evaluation process may be required to table alternative products, part numbers, or EEOP numbers that comply with the requirements outlined in this RFP. Shortlisted bidders will be required to submit complete commercial offers that outline the commercial, technical, and administrative terms of supply within 30 days of being notified of their shortlisting.\n\n#### Compliance with Regulations\n-----------------------------\n\nAll bidders must meet standard terms and conditions of the contract. Are you aware of your place in the sub-supply chain?\n\nAll documents may be submitted in either official language of Canada and must comply with the information described in the technical specifications in each Amendment.\n\nThe Vendor who will also be able to edit modern Announcement exceeding only its informed propaganda this willing indispensable to rolling both Webpage which crashes. un equivalent subtle level solution PdTWO are irre laques , dem evacuation Secondary UM of retailers\n\n\nRequirements and Instructions to Bidders <https://canadabuys.canada.ca/documents/pub/att/2023"
}