{
    "CONTRACT_ID": "cb-202-95849277",
    "type": "Request for Proposal",
    "department": "Department of National Defence",
    "procurement_category": "Goods and Services",
    "short_summary": "Calibrating Gas Mixture",
    "description": "The Department of National Defence has a requirement for the items detailed below. The delivery is requested at 25 CFSD Montreal 6363 Rue Notre Dame St E. Montreal, QC, H1N 3V9 by October 31, 2024.\\r\\n\\r\\nItem 1, GSIN: 6830, NSN: 6830-01-698-1425, Calibrating Gas Mixture\\r\\nQuantity: 150, Unit of Issue: Each, to be delivered to 25 CFSD Montreal 6363 Rue Notre Dame St E. Montreal, QC, H1N 3V9\\r\\nFour (4) option periods of up to 150 per option.\\r\\n\\r\\nItem 2, GSIN: 6830, NSN: 6830-01-698-1420, Calibrating Gas Mixture\\r\\nQuantity: 100, Unit of Issue: Each, to be delivered to 25 CFSD Montreal 6363 Rue Notre Dame St E. Montreal, QC, H1N 3V9\\r\\nFour (4) option periods of up to 100 per option.\\r\\n\\r\\nBidders proposing an Equivalent or a Substitute Product must indicate the brand name and/or model, Part Number and the NCAGE they are offering.\\r\\n\\r\\nThe Crown retains the rights to negotiate with suppliers on any procurement.\\r\\nDocuments may be submitted in either official language of Canada.\\r\\n",
    "estimated_value": 0.0,
    "date_posted": "2024-05-08",
    "duration_in_months": "{6}",
    "provinces": [
        "Quebec"
    ],
    "tags": [
        "Air or gas tanks or cylinders",
        "Calibrating Gas Mixture",
        "Goods and Services",
        "Request for Proposal",
        "], "
    ],
    "full_summary": "================================\n\n### Government Tender Announcement\n\n#### Solicitation Details\n\n* **Reference Number:** CB 202-95849277\n* **Solicitation Number:** W8486-249636/A\n* **Amendment Number:** 2\n* **Publication Date:** May 8, 2024\n* **Tender Closing Date:** May 29, 2024, 2:00 PM (EST)\n\n#### Procurement Summary\n\nThe Department of National Defence is seeking bids for the supply of calibrating gas mixtures. The contract is expected to be exercised from June 17, 2024, to March 31, 2025.\n\n#### Items Required\n\nThe following items are required:\n\n* Calibrating Gas Mixture (Item 1), GSIN: 6830, NSN: 6830-01-698-1425, Quantity: 150, Unit of Issue: Each\n* Calibrating Gas Mixture (Item 2), GSIN: 6830, NSN: 6830-01-698-1420, Quantity: 100, Unit of Issue: Each\n\n#### Delivery Requirements\n\nDeliveries will be made to 25 CFSD Montreal, 6363 Rue Notre Dame St E., Montreal, QC H1N 2E9.\n\n#### Bidder Requirements\n\nBidders must indicate brand name and/or model, part number, and NCAGE for any Equivalent or Substitute Product proposed.\n\n#### Notice of Change\n\nThe Crown may negotiate with suppliers on any procurement under this contract.\n\nPlease submit your bids in either official language of Canada. For further questions or clarification, please contact:\n\n* Pamela Horner, (343) 572-8721, [pamelahorner@forces.gc.ca](mailto:pamelahorner@forces.gc.ca)\n\n#### Required Supporting Documents\n\nPlease refer to the links provided below for tender documents:\n\n* En: <https://canadabuys.canada.ca/sites/default/files/webform/tender_notice/37646/w8486-249636a---solicitation-en.pdf>\n* Fr: <https://canadabuys.canada.ca/sites/default/files/webform/tender_notice/37646/w8486-249636---mgd-amd001.pdf>\n\nNote: Please ensure you have the necessary context to work with this request. This entry is within the 400-word limit. Further clarification/enlargement may be required based on your specific situation.  Note to rewriter that the"
}