{
    "CONTRACT_ID": "S5008425",
    "type": "Temporary Help Services",
    "department": "Department of National Defense",
    "procurement_category": "SRV",
    "short_summary": "",
    "description": "",
    "estimated_value": 0,
    "date_posted": "2024-07-08",
    "duration_in_months": ":{",
    "provinces": [
        "Ontario"
    ],
    "tags": [
        "Temporary Personnel Services",
        "Secret Security Requirement"
    ],
    "full_summary": "**Government Tender Announcement: Temporary Help Services (THS)**\n===========================================================\n\n### Mandatory Information\n\n* **Tender Reference:** CB-249-72571786\n* **Solicitation Reference:** S5008425\n* **Publication Date:** 2024-07-08\n* **Tender Closing Date:** 2024-07-15 15:00:00\n* **Expected Contract Start Date:** None\n* **Expected Contract End Date:** None\n* **Tender Status:** Exired\n\n### Description of the Requirement\n\nThe Department of National Defense (DND) is soliciting Temporary Help Services (THS) under the Supply Arrangement EN578-172870. This requirement is specifically for Computer Application Support (Stream 5.1) under the Temporary Personnel Services (UNSCLASS) category.\n\n### Eligibility Criteria\n\nOnly suppliers listed under the Supply Arrangement EN578-172870 and qualified under the mentioned streams and categories may participate in this tender.\n\n### Description of the Requirement\n\nDND requires Temporary Help Services to support its IT operations. This request is addressed to suppliers who have been invited to submit a proposal for the provision of Computer Application Support services.\n\n### Level of Security Requirement\n\nThe minimum level of security required for this requirement is Secret.\n\n### Contact Information\n\n* **Contact Name:** CFSG(O-G) Temp Help\n* **Email:** CFSGO-GTemporaryHelp-GSFCO-G-daide[temporai]re@forces.gc.ca\n* **Phone:** (613) 971-7955\n\n### Documents and Attachments\n\nThe tender notice and request for proposal can be found on the Canada Buys website: [https://canadabuys.canada.ca/sites/default/files/webform/tender_notice/40429/s5008425--rfp_1.pdf](https://canadabuys.canada.ca/sites/default/files/webform/tender_notice/40429/s5008425--rfp_1.pdf)\n\n### Trade Agreements and Regions of Opportunity\n\n* **Trade Agreements:** Canadian Free Trade Agreement (CFTA) and Comprehesive and Progressive Agreement for Trans-Pacific Partnership (CPTPP)\n* **Regions of Opportunity:** National Capital Region (NCR)\n* **Regions of Delivery:** National Capital Region (NCR)\n\n### Amendments and Cancellations\n\nThis tender announcement has been updated on 2024-07-15. The solicitation number remains the same. No cancellations have been made to this tender announcement. \n\n"
}