{
    "CONTRACT_ID": "PW-22-01003817",
    "type": "REQUEST FOR PROPOSAL",
    "department": "CANADIAN FOOD INSPECTION AGENCY",
    "procurement_category": "_GENERALconditions_of_contract_applicable*gdfocaleTerm\u03c4\u03b5\u03c1\u03bfcitationS * GD",
    "short_summary": "CFIA Ottawa Lab Fallowfield has a need for a Reverse Vertical Laminar Flow Cabinet",
    "description": "THIS REQUEST IS RESERVED FOR HOLDERS OF SUPPLY ARRANGEMENT # E60PV-19EQUI ONLY, FOR THE PURCHASE OF LABORATORY AND SCIENTIFIC EQUIPMENT, PARTS AND ACCESSORIES, SERVICES AND SUPPLIES.",
    "estimated_value": 0.0,
    "date_posted": "08/09/2022",
    "duration_in_months": "But the duration of the contract is not available.",
    "provinces": [
        "Ontario"
    ],
    "tags": [
        "canada",
        "canadian free trade agreement *(cfta)",
        "laboratory equipment",
        "reverse vertical laminar flow cabinet",
        "canadian food inspection agency"
    ],
    "full_summary": "**Government Tender Announcement**\n\n* **Reference Number:** PW-22-01003817\n* **Solicitation Number:** 2023-00384\n* **Publication Date:** August 9, 2022\n* **Tender Closing Date:** September 19, 2022, at 2:00 PM Eastern Time\n* **Contracting Entity:** Canadian Food Inspection Agency\n* **Location:** National Capital Region (NCR), Canada\n* **Notice Type:** Request for Proposal\n* **Procurement Category:** Goods and Services\n* **Trade Agreements:** Canadian Free Trade Agreement (CFTA)\n\n**Tender Description:**\nThe Canadian Food Inspection Agency (CFIA) is seeking a supplier to provide a Reverse Vertical Laminar Flow Cabinet for use in the Ottawa Lab Fallowfield. This opportunity is reserved for suppliers who have a valid Supply Arrangement # E60PV-19EQUI for Laboratory and Scientific Equipment, Parts and Accessories, Services and Supplies with Public Works and Government Services Canada.\n\nSuppliers interested in submitting a bid must:\n\n1. Be pre-qualified on Supply Arrangement # E60PV-19EQUI for Laboratory and Scientific Equipment, Parts and Accessories, Services and Supplies\n2. Download the solicitation document E60PV-19EQUI /C from Buyandsell.gc.ca\n3. Submit a response as per the requirements of the Request for Supply Arrangement\n\nPlease note that suppliers who do not have a valid Supply Arrangement for the aforementioned commodities cannot submit a bid. Any bids received from such suppliers will not be evaluated.\n\n**Documents:**\nThe solicitation document and associated information can be accessed through the following links:\n\n* English: https://canadabuys.canada.ca/documents/pub/att/2022/08/09/311fc3188be56f80d78c595794ef2e71/2023-00384-npp_english.pdf\n* French: https://canadabuys.canada.ca/documents/pub/att/2022/08/09/2bc0275c225658b93d6b1d8a7d798c2e/2023-00384-npp_french.pdf\n\n**Contact Information:**\nFor further information or clarification on this tender, please contact:\n\nAlexander Lisowski\nEmail: [Alexander.lisowski@inspection.gc.ca](mailto:Alexander.lisowski@inspection.gc.ca)\n\nNote: The contact phone and fax numbers are not provided as they were not"
}