{
    "CONTRACT_ID": "PW-_PPS-028-28806",
    "type": "Bid Solicitation",
    "department": "Public Works and Government Services Canada",
    "procurement_category": "General Contract",
    "short_summary": "Relacement of metal cladding, trim, and sealant on the roof skylight at the Bank of Nova Scotia building",
    "description": "The project consists of replacing the metal cladding, trim, and sealant on the roof skylight at the Bank of Nova Scotia building. Work is to be completed within 8 Weeks after contract award.",
    "estimated_value": 0,
    "date_posted": "2022-09-14",
    "duration_in_months": "0",
    "provinces": [
        "Ontario"
    ],
    "tags": [
        "skylight",
        "metal cladding",
        "replacing",
        "roof",
        "Nova Scotia",
        "Bank of Nova Scotia",
        "trimage",
        "scalding",
        " Canada ",
        "government",
        "department",
        "governmental",
        "public",
        "solicitation",
        "bids",
        "bid solicitation",
        "to extend the deadline",
        "visite de site ",
        "Earth",
        " courthouse",
        " municipalities"
    ],
    "full_summary": "## Skylight Metal Cladding Replacement\n### Bid Invitation\n#### Invitation to Bid: EP807-230706/A\n\nProject Description:\nReplace metal cladding, trim, and sealant on the roof skylight at the Bank of Nova Scotia building.\n\n**Duration of the Contract:** 8 weeks\n\n**Bid Submission:**\n\n\u2022 Interested suppliers may submit a bid\n\u2022 Bid documents can be obtained via [Buyandsell.gc.ca/tenders](http://Buyandsell.gc.ca/tenders) or [1-855-886-3030](tel:1-855-886-3030)\n\u2022 Sealed bids will be received at: Public Works and Government Services Canada, Bid Receiving Unit, Place du Portage, Phase III, Main Lobby Core 0B2, 11 Laurier Street, Gatineau, Quebec, K1A 1C9\n\n**Clauses of Participation:**\n\n#### Mandatory Security Requirements:\n\u2022 Hold a valid SITE ACCESS Clearance, granted or approved by the Contract Security Program (CSP), Public Works and Government Services (PWGSC)\n\n#### Access Visits:\nTwo site visits were conducted on:\n1. **23/09/2022**: Interested bidders attended the mandatory site visit.\n2. **01/11/2022**: An additional site visit was held.\n\n#### Enquiries:\nEnquiries can be submitted to Mike Stirling by email at [mike.stirling@tpsgc-pwgsc.gc.ca](mailto:mike.stirling@tpsgc-pwgsc.gc.ca). Last submission date for ENQUIRIES is five (3) business days prior to the closing date.\n\n#### Contract Document:\nContract documents are available on [Buyandsell.gc.ca/tenders](http://Buyandsell.gc.ca/tenders)\n\n#### Submission Payments:\nPurchases are to be made in accordance with the provided documents. Please consult [Buyandsell.gc.ca/tenders](http://Buyandsell.gc.ca/tenders) for queries.\n\n**Security:**\nEntrants comply with the Security Requirements Check List and security guide attached to Annex A.\n\n### Important Details:\n\n* **Trade Agreement:** CFTA and CTPP\n* **Closing Time and Date:** November 21, 2022, at 2:00 p.m.\n* **delivery date:** September 13, 2022\n* Files are available at the home page to view supporting documents\n\nCanada allots the User Fees Act. CIDB Level 6 procedure Applied CIDB Construction Lew required aided with"
}