{
    "CONTRACT_ID": "WS3696558429-Doc3697280215",
    "type": "amendment",
    "department": "Public Works and Government Services Canada",
    "procurement_category": "SRV",
    "short_summary": "Technical Advisor services in support of Alexandra Bridge Replacement Project",
    "description": "AMENDMENT TO CLOSING TIME: ...",
    "estimated_value": 11,
    "date_posted": "2022-10-06",
    "duration_in_months": "That position will be for 11 years",
    "provinces": [
        "Quebec"
    ],
    "tags": [
        "WPSPC",
        " Alexandra Bridge",
        " Technical Advisor",
        " Public Works and Government Services Canada (PWGSC)"
    ]
}