{
    "CONTRACT_ID": "WS3697744913-Doc3845360355",
    "type": "JSON",
    "department": "Minist\u00e8re des travaux publics et des services gouvernementaux (SPAC) ",
    "procurement_category": "Service",
    "short_summary": "Water transportation services to and from the Atlantic Research Centre's Acoustic Calibration Laboratory (ACL) with operator. ",
    "description": "The Department of Defence Research and Development Canada (DRDC) is seeking a contract for water transportation services to and from the Atlantic Research Centre\u2019s Acoustic Calibration Laboratory (ACL) with operator.",
    "estimated_value": 1000000,
    "date_posted": "2023/01/30",
    "duration_in_months": "So ",
    "provinces": [
        "Quebec"
    ],
    "tags": [
        "CFTA",
        "Canada OPS"
    ]
}