{
    "CONTRACT_ID": "Some Modified Version of the Contract ID",
    "type": "GROUPED PURCHASING NEWS NOTIFICATION FOR EQUIPMENT AND INFORMATION TECHNOLOGY SUPPLIES RELEASED BY ELIGIBLE SUPPLIES, TECHNICAL SERVICES - ESSSP shared",
    "department": "Royal Canadian Mounted Police - RCOMP",
    "procurement_category": "Goods",
    "short_summary": "Northern Lights Town Hall",
    "description": "Joint Annual Northern Lights Convention",
    "estimated_value": 25000.0,
    "date_posted": "2022-05-24",
    "duration_in_months": "), 0.0 - If unbundled, the products or services must be supplied over a duration of no less than 3 months and no more than 24 months.",
    "provinces": [
        "Ontario"
    ],
    "tags": [
        "Ontario",
        "Royal Canadian Mounted Police - RCOMP",
        "Goods",
        "Purchase Request-Solicitation"
    ]
}